gluex_lumi/__init__.py
gluex_lumi/__init__.pyi
gluex_lumi/gluex_lumi.cpython-313t-x86_64-linux-musl.so
gluex_lumi/py.typed
gluex_lumi-0.1.8.dist-info/METADATA
gluex_lumi-0.1.8.dist-info/WHEEL
gluex_lumi-0.1.8.dist-info/entry_points.txt
gluex_lumi.libs/libgcc_s-f685abf1.so.1
gluex_lumi-0.1.8.dist-info/RECORD
